atomisticparsers/__init__.py
atomisticparsers/amber/README.md
atomisticparsers/amber/__init__.py
atomisticparsers/amber/__main__.py
atomisticparsers/amber/nomad_plugin.yaml
atomisticparsers/amber/parser.py
atomisticparsers/amber/metainfo/__init__.py
atomisticparsers/amber/metainfo/amber.py
atomisticparsers/asap/README.md
atomisticparsers/asap/__init__.py
atomisticparsers/asap/__main__.py
atomisticparsers/asap/nomad_plugin.yaml
atomisticparsers/asap/parser.py
atomisticparsers/asap/metainfo/__init__.py
atomisticparsers/asap/metainfo/asap.py
atomisticparsers/ase/__init__.py
atomisticparsers/ase/__main__.py
atomisticparsers/ase/parser.py
atomisticparsers/bopfox/README.md
atomisticparsers/bopfox/__init__.py
atomisticparsers/bopfox/__main__.py
atomisticparsers/bopfox/nomad_plugin.yaml
atomisticparsers/bopfox/parser.py
atomisticparsers/bopfox/metainfo/__init__.py
atomisticparsers/bopfox/metainfo/bopfox.py
atomisticparsers/dftbplus/README.md
atomisticparsers/dftbplus/__init__.py
atomisticparsers/dftbplus/__main__.py
atomisticparsers/dftbplus/nomad_plugin.yaml
atomisticparsers/dftbplus/parser.py
atomisticparsers/dftbplus/metainfo/__init__.py
atomisticparsers/dftbplus/metainfo/dftbplus.py
atomisticparsers/dlpoly/README.md
atomisticparsers/dlpoly/__init__.py
atomisticparsers/dlpoly/__main__.py
atomisticparsers/dlpoly/nomad_plugin.yaml
atomisticparsers/dlpoly/parser.py
atomisticparsers/dlpoly/metainfo/__init__.py
atomisticparsers/dlpoly/metainfo/dl_poly.py
atomisticparsers/gromacs/README.md
atomisticparsers/gromacs/__init__.py
atomisticparsers/gromacs/__main__.py
atomisticparsers/gromacs/nomad_plugin.yaml
atomisticparsers/gromacs/parser.py
atomisticparsers/gromacs/metainfo/__init__.py
atomisticparsers/gromacs/metainfo/gromacs.py
atomisticparsers/gromos/README.md
atomisticparsers/gromos/__init__.py
atomisticparsers/gromos/__main__.py
atomisticparsers/gromos/nomad_plugin.yaml
atomisticparsers/gromos/parser.py
atomisticparsers/gromos/metainfo/__init__.py
nomad_parser_plugins_atomistic-1.0.10.dist-info/licenses/LICENSE
nomad_parser_plugins_atomistic-1.0.10.dist-info/METADATA
nomad_parser_plugins_atomistic-1.0.10.dist-info/WHEEL
nomad_parser_plugins_atomistic-1.0.10.dist-info/entry_points.txt
nomad_parser_plugins_atomistic-1.0.10.dist-info/top_level.txt
nomad_parser_plugins_atomistic-1.0.10.dist-info/RECORD
