Metadata-Version: 2.4
Name: nomad-parser-plugins-atomistic
Version: 1.0.10
Summary: Collection of NOMAD parsers for atomistic codes.
Author: The NOMAD Authors
License: 
Project-URL: homepage, https://github.com/nomad-coe/atomistic-parsers
License-File: LICENSE
Requires-Dist: nomad-lab>=1.3.13
Requires-Dist: nomad-schema-plugin-simulation-workflow>=1.0.1
Requires-Dist: nomad-schema-plugin-run>=1.0.1
Requires-Dist: nomad-parser-plugins-simulation>=1.0.2
Requires-Dist: lxml>=5.2
Requires-Dist: mdanalysis<3.0,>=2.8.0; python_full_version >= "3.10"
Requires-Dist: mdanalysis<2.8; python_full_version < "3.10"
Requires-Dist: panedr>=0.2
Requires-Dist: scipy>=1.7.1
Requires-Dist: pydantic>=1.10.8
Requires-Dist: ase>=3.22.0
Requires-Dist: numpy>=1.22.4
Requires-Dist: h5py>=3.6.0
Provides-Extra: dev
Requires-Dist: pytest; extra == "dev"
Requires-Dist: pytest-cov; extra == "dev"
Requires-Dist: astroid>=2.5.1; extra == "dev"
Requires-Dist: mypy>=1.15; extra == "dev"
Requires-Dist: ruff; extra == "dev"
Requires-Dist: typing-extensions>=4.12; extra == "dev"
Provides-Extra: infrastructure
Requires-Dist: nomad-lab[infrastructure]>=1.3.10; extra == "infrastructure"
Dynamic: license-file
